smartdiffusion/__init__.py
smartdiffusion/checkpoint_pickle.py
smartdiffusion/cli_args.py
smartdiffusion/clip_model.py
smartdiffusion/clip_vision.py
smartdiffusion/conds.py
smartdiffusion/config.py
smartdiffusion/controlnet.py
smartdiffusion/diffusers_convert.py
smartdiffusion/diffusers_load.py
smartdiffusion/folder_paths.py
smartdiffusion/gligen.py
smartdiffusion/latent_formats.py
smartdiffusion/latent_preview.py
smartdiffusion/load.py
smartdiffusion/lora.py
smartdiffusion/model_base.py
smartdiffusion/model_detection.py
smartdiffusion/model_management.py
smartdiffusion/model_patcher.py
smartdiffusion/model_sampling.py
smartdiffusion/node_helpers.py
smartdiffusion/nodes.py
smartdiffusion/ops.py
smartdiffusion/options.py
smartdiffusion/sample.py
smartdiffusion/sampler_helpers.py
smartdiffusion/samplers.py
smartdiffusion/sd.py
smartdiffusion/sd1_clip.py
smartdiffusion/sdxl_clip.py
smartdiffusion/supported_models.py
smartdiffusion/supported_models_base.py
smartdiffusion/types.py
smartdiffusion/utils.py
smartdiffusion/class/nodes/CLIPLoader.py
smartdiffusion/class/nodes/CLIPSetLastLayer.py
smartdiffusion/class/nodes/CLIPTextEncode.py
smartdiffusion/class/nodes/CLIPVisionEncode.py
smartdiffusion/class/nodes/CLIPVisionLoader.py
smartdiffusion/class/nodes/CheckpointLoader.py
smartdiffusion/class/nodes/CheckpointLoaderSimple.py
smartdiffusion/class/nodes/ConditioningAverage.py
smartdiffusion/class/nodes/ConditioningCombine.py
smartdiffusion/class/nodes/ConditioningConcat.py
smartdiffusion/class/nodes/ConditioningSetArea.py
smartdiffusion/class/nodes/ConditioningSetAreaPercentage.py
smartdiffusion/class/nodes/ConditioningSetAreaStrength.py
smartdiffusion/class/nodes/ConditioningSetMask.py
smartdiffusion/class/nodes/ConditioningSetTimestepRange.py
smartdiffusion/class/nodes/ConditioningZeroOut.py
smartdiffusion/class/nodes/ControlNetApply.py
smartdiffusion/class/nodes/ControlNetApplyAdvanced.py
smartdiffusion/class/nodes/ControlNetLoader.py
smartdiffusion-0.0.3.dist-info/LICENSE
smartdiffusion-0.0.3.dist-info/METADATA
smartdiffusion-0.0.3.dist-info/WHEEL
smartdiffusion-0.0.3.dist-info/top_level.txt
smartdiffusion-0.0.3.dist-info/RECORD
